[

	{
		"date" : "2011-11-16",
		"nav" : "123.693000"
    
	},
    
	{
		"date" : "2011-11-23",
		"nav" : "117.321000"
    
	},
    
	{
		"date" : "2011-11-30",
		"nav" : "119.741000"
    
	},
    
	{
		"date" : "2011-12-08",
		"nav" : "121.347000"
    
	},
    
	{
		"date" : "2011-12-15",
		"nav" : "116.853000"
    
	},
    
	{
		"date" : "2011-12-22",
		"nav" : "115.437000"
    
	},
    
	{
		"date" : "2011-12-29",
		"nav" : "113.960000"
    
	},
    
	{
		"date" : "2012-01-05",
		"nav" : "116.492000"
    
	},
    
	{
		"date" : "2012-01-12",
		"nav" : "117.276000"
    
	},
    
	{
		"date" : "2012-01-19",
		"nav" : "120.945000"
    
	},
    
	{
		"date" : "2012-01-27",
		"nav" : "125.546000"
    
	},
    
	{
		"date" : "2012-02-03",
		"nav" : "128.892000"
    
	},
    
	{
		"date" : "2012-02-10",
		"nav" : "132.234000"
    
	},
    
	{
		"date" : "2012-02-17",
		"nav" : "136.825000"
    
	},
    
	{
		"date" : "2012-02-27",
		"nav" : "131.209000"
    
	},
    
	{
		"date" : "2012-03-05",
		"nav" : "132.670000"
    
	},
    
	{
		"date" : "2012-03-13",
		"nav" : "135.364000"
    
	},
    
	{
		"date" : "2012-03-20",
		"nav" : "131.508000"
    
	},
    
	{
		"date" : "2012-03-27",
		"nav" : "131.557000"
    
	},
    
	{
		"date" : "2012-04-03",
		"nav" : "135.446000"
    
	},
    
	{
		"date" : "2012-04-12",
		"nav" : "133.377000"
    
	},
    
	{
		"date" : "2012-04-19",
		"nav" : "134.558000"
    
	},
    
	{
		"date" : "2012-04-26",
		"nav" : "132.507000"
    
	},
    
	{
		"date" : "2012-05-04",
		"nav" : "129.814000"
    
	},
    
	{
		"date" : "2012-05-11",
		"nav" : "125.954000"
    
	},
    
	{
		"date" : "2012-05-18",
		"nav" : "124.661000"
    
	},
    
	{
		"date" : "2012-05-25",
		"nav" : "125.391000"
    
	},
    
	{
		"date" : "2012-06-01",
		"nav" : "124.144000"
    
	},
    
	{
		"date" : "2012-06-08",
		"nav" : "127.663000"
    
	},
    
	{
		"date" : "2012-06-15",
		"nav" : "128.584000"
    
	},
    
	{
		"date" : "2012-06-22",
		"nav" : "128.983000"
    
	},
    
	{
		"date" : "2012-06-29",
		"nav" : "131.509000"
    
	},
    
	{
		"date" : "2012-07-06",
		"nav" : "132.930000"
    
	},
    
	{
		"date" : "2012-07-13",
		"nav" : "132.078000"
    
	},
    
	{
		"date" : "2012-07-20",
		"nav" : "131.390000"
    
	},
    
	{
		"date" : "2012-07-27",
		"nav" : "128.043000"
    
	},
    
	{
		"date" : "2012-08-03",
		"nav" : "130.115000"
    
	},
    
	{
		"date" : "2012-08-10",
		"nav" : "130.510000"
    
	},
    
	{
		"date" : "2012-08-21",
		"nav" : "132.838000"
    
	},
    
	{
		"date" : "2012-08-28",
		"nav" : "131.297000"
    
	},
    
	{
		"date" : "2012-09-04",
		"nav" : "131.040000"
    
	},
    
	{
		"date" : "2012-09-11",
		"nav" : "133.860000"
    
	},
    
	{
		"date" : "2012-09-18",
		"nav" : "138.326000"
    
	},
    
	{
		"date" : "2012-09-26",
		"nav" : "140.295000"
    
	},
    
	{
		"date" : "2012-10-04",
		"nav" : "143.781000"
    
	},
    
	{
		"date" : "2012-10-11",
		"nav" : "142.294000"
    
	},
    
	{
		"date" : "2012-10-18",
		"nav" : "141.858000"
    
	},
    
	{
		"date" : "2012-10-26",
		"nav" : "140.277000"
    
	},
    
	{
		"date" : "2012-11-02",
		"nav" : "140.352000"
    
	},
    
	{
		"date" : "2012-11-09",
		"nav" : "139.206000"
    
	},
    
	{
		"date" : "2012-11-20",
		"nav" : "136.067000"
    
	},
    
	{
		"date" : "2012-11-27",
		"nav" : "139.886000"
    
	},
    
	{
		"date" : "2012-12-05",
		"nav" : "144.310000"
    
	},
    
	{
		"date" : "2012-12-12",
		"nav" : "144.589000"
    
	},
    
	{
		"date" : "2012-12-19",
		"nav" : "145.392000"
    
	},
    
	{
		"date" : "2012-12-27",
		"nav" : "145.212000"
    
	},
    
	{
		"date" : "2013-01-03",
		"nav" : "149.618000"
    
	},
    
	{
		"date" : "2013-01-10",
		"nav" : "149.686000"
    
	},
    
	{
		"date" : "2013-01-17",
		"nav" : "151.583000"
    
	},
    
	{
		"date" : "2013-01-24",
		"nav" : "150.842000"
    
	},
    
	{
		"date" : "2013-01-31",
		"nav" : "151.118000"
    
	},
    
	{
		"date" : "2013-02-07",
		"nav" : "147.686000"
    
	},
    
	{
		"date" : "2013-02-14",
		"nav" : "147.296000"
    
	},
    
	{
		"date" : "2013-02-21",
		"nav" : "145.632000"
    
	},
    
	{
		"date" : "2013-02-28",
		"nav" : "143.103000"
    
	},
    
	{
		"date" : "2013-03-07",
		"nav" : "147.627000"
    
	},
    
	{
		"date" : "2013-03-14",
		"nav" : "148.160000"
    
	},
    
	{
		"date" : "2013-03-21",
		"nav" : "143.375000"
    
	},
    
	{
		"date" : "2013-04-01",
		"nav" : "143.718000"
    
	},
    
	{
		"date" : "2013-04-08",
		"nav" : "139.982000"
    
	},
    
	{
		"date" : "2013-04-15",
		"nav" : "139.898000"
    
	},
    
	{
		"date" : "2013-04-23",
		"nav" : "144.738000"
    
	},
    
	{
		"date" : "2013-05-02",
		"nav" : "147.332000"
    
	},
    
	{
		"date" : "2013-05-09",
		"nav" : "149.343000"
    
	},
    
	{
		"date" : "2013-05-16",
		"nav" : "151.929000"
    
	},
    
	{
		"date" : "2013-05-23",
		"nav" : "147.581000"
    
	},
    
	{
		"date" : "2013-05-30",
		"nav" : "150.699000"
    
	},
    
	{
		"date" : "2013-06-06",
		"nav" : "148.357000"
    
	},
    
	{
		"date" : "2013-06-13",
		"nav" : "143.004000"
    
	},
    
	{
		"date" : "2013-06-20",
		"nav" : "141.829000"
    
	},
    
	{
		"date" : "2013-06-27",
		"nav" : "139.866000"
    
	},
    
	{
		"date" : "2013-07-04",
		"nav" : "143.283000"
    
	},
    
	{
		"date" : "2013-07-11",
		"nav" : "144.364000"
    
	},
    
	{
		"date" : "2013-07-18",
		"nav" : "146.742000"
    
	},
    
	{
		"date" : "2013-07-25",
		"nav" : "144.677000"
    
	},
    
	{
		"date" : "2013-08-01",
		"nav" : "140.221000"
    
	},
    
	{
		"date" : "2013-08-08",
		"nav" : "136.490000"
    
	},
    
	{
		"date" : "2013-08-19",
		"nav" : "133.850000"
    
	},
    
	{
		"date" : "2013-08-26",
		"nav" : "134.797000"
    
	},
    
	{
		"date" : "2013-09-02",
		"nav" : "135.797000"
    
	},
    
	{
		"date" : "2013-09-10",
		"nav" : "142.940000"
    
	},
    
	{
		"date" : "2013-09-17",
		"nav" : "142.038000"
    
	},
    
	{
		"date" : "2013-09-24",
		"nav" : "142.661000"
    
	},
    
	{
		"date" : "2013-10-01",
		"nav" : "141.835000"
    
	},
    
	{
		"date" : "2013-10-09",
		"nav" : "147.435000"
    
	},
    
	{
		"date" : "2013-10-17",
		"nav" : "149.399000"
    
	},
    
	{
		"date" : "2013-10-24",
		"nav" : "152.784000"
    
	},
    
	{
		"date" : "2013-10-31",
		"nav" : "157.232000"
    
	},
    
	{
		"date" : "2013-11-08",
		"nav" : "155.975000"
    
	},
    
	{
		"date" : "2013-11-18",
		"nav" : "156.285000"
    
	},
    
	{
		"date" : "2013-11-25",
		"nav" : "155.375000"
    
	},
    
	{
		"date" : "2013-12-02",
		"nav" : "158.864000"
    
	},
    
	{
		"date" : "2013-12-09",
		"nav" : "162.227000"
    
	},
    
	{
		"date" : "2013-12-16",
		"nav" : "158.081000"
    
	},
    
	{
		"date" : "2013-12-23",
		"nav" : "161.649000"
    
	},
    
	{
		"date" : "2013-12-31",
		"nav" : "162.886000"
    
	},
    
	{
		"date" : "2014-01-07",
		"nav" : "160.275000"
    
	},
    
	{
		"date" : "2014-01-14",
		"nav" : "162.527000"
    
	},
    
	{
		"date" : "2014-01-21",
		"nav" : "163.644000"
    
	},
    
	{
		"date" : "2014-01-28",
		"nav" : "158.858000"
    
	},
    
	{
		"date" : "2014-02-04",
		"nav" : "157.102000"
    
	},
    
	{
		"date" : "2014-02-11",
		"nav" : "158.681000"
    
	},
    
	{
		"date" : "2014-02-18",
		"nav" : "161.353000"
    
	},
    
	{
		"date" : "2014-02-25",
		"nav" : "163.649000"
    
	},
    
	{
		"date" : "2014-03-05",
		"nav" : "167.517000"
    
	},
    
	{
		"date" : "2014-03-12",
		"nav" : "171.107000"
    
	},
    
	{
		"date" : "2014-03-20",
		"nav" : "170.822000"
    
	},
    
	{
		"date" : "2014-03-27",
		"nav" : "175.272000"
    
	},
    
	{
		"date" : "2014-04-03",
		"nav" : "179.329000"
    
	},
    
	{
		"date" : "2014-04-11",
		"nav" : "180.732000"
    
	},
    
	{
		"date" : "2014-04-22",
		"nav" : "182.291000"
    
	},
    
	{
		"date" : "2014-04-30",
		"nav" : "180.482000"
    
	},
    
	{
		"date" : "2014-05-08",
		"nav" : "181.359000"
    
	},
    
	{
		"date" : "2014-05-15",
		"nav" : "190.441000"
    
	},
    
	{
		"date" : "2014-05-22",
		"nav" : "197.422000"
    
	},
    
	{
		"date" : "2014-05-29",
		"nav" : "197.657000"
    
	},
    
	{
		"date" : "2014-06-05",
		"nav" : "206.059000"
    
	},
    
	{
		"date" : "2014-06-12",
		"nav" : "211.414000"
    
	},
    
	{
		"date" : "2014-06-19",
		"nav" : "209.885000"
    
	},
    
	{
		"date" : "2014-06-26",
		"nav" : "207.669000"
    
	},
    
	{
		"date" : "2014-07-03",
		"nav" : "215.847000"
    
	},
    
	{
		"date" : "2014-07-10",
		"nav" : "211.157000"
    
	},
    
	{
		"date" : "2014-07-17",
		"nav" : "215.691000"
    
	},
    
	{
		"date" : "2014-07-24",
		"nav" : "219.090000"
    
	},
    
	{
		"date" : "2014-08-01",
		"nav" : "213.828000"
    
	},
    
	{
		"date" : "2014-08-08",
		"nav" : "213.155000"
    
	},
    
	{
		"date" : "2014-08-18",
		"nav" : "222.345000"
    
	},
    
	{
		"date" : "2014-08-25",
		"nav" : "222.977000"
    
	},
    
	{
		"date" : "2014-09-02",
		"nav" : "230.201000"
    
	},
    
	{
		"date" : "2014-09-09",
		"nav" : "233.375000"
    
	},
    
	{
		"date" : "2014-09-16",
		"nav" : "228.765000"
    
	},
    
	{
		"date" : "2014-09-23",
		"nav" : "229.044000"
    
	},
    
	{
		"date" : "2014-09-30",
		"nav" : "227.188000"
    
	},
    
	{
		"date" : "2014-10-10",
		"nav" : "222.819000"
    
	},
    
	{
		"date" : "2014-10-20",
		"nav" : "221.537000"
    
	},
    
	{
		"date" : "2014-10-29",
		"nav" : "228.045000"
    
	},
    
	{
		"date" : "2014-11-07",
		"nav" : "235.474000"
    
	},
    
	{
		"date" : "2014-11-14",
		"nav" : "236.595000"
    
	},
    
	{
		"date" : "2014-11-21",
		"nav" : "240.537000"
    
	},
    
	{
		"date" : "2014-11-28",
		"nav" : "243.119000"
    
	},
    
	{
		"date" : "2014-12-05",
		"nav" : "242.685000"
    
	},
    
	{
		"date" : "2014-12-12",
		"nav" : "232.963000"
    
	},
    
	{
		"date" : "2014-12-19",
		"nav" : "233.182000"
    
	},
    
	{
		"date" : "2014-12-29",
		"nav" : "233.740000"
    
	},
    
	{
		"date" : "2015-01-05",
		"nav" : "238.526000"
    
	},
    
	{
		"date" : "2015-01-12",
		"nav" : "236.190000"
    
	},
    
	{
		"date" : "2015-01-19",
		"nav" : "239.979000"
    
	},
    
	{
		"date" : "2015-01-27",
		"nav" : "248.121000"
    
	},
    
	{
		"date" : "2015-02-03",
		"nav" : "242.983000"
    
	},
    
	{
		"date" : "2015-02-10",
		"nav" : "236.446000"
    
	},
    
	{
		"date" : "2015-02-18",
		"nav" : "244.400000"
    
	},
    
	{
		"date" : "2015-02-25",
		"nav" : "241.706000"
    
	},
    
	{
		"date" : "2015-03-04",
		"nav" : "246.229000"
    
	},
    
	{
		"date" : "2015-03-12",
		"nav" : "245.197000"
    
	},
    
	{
		"date" : "2015-03-19",
		"nav" : "241.513000"
    
	},
    
	{
		"date" : "2015-03-26",
		"nav" : "232.314000"
    
	},
    
	{
		"date" : "2015-04-06",
		"nav" : "241.678000"
    
	},
    
	{
		"date" : "2015-04-13",
		"nav" : "247.712000"
    
	},
    
	{
		"date" : "2015-04-21",
		"nav" : "238.543000"
    
	},
    
	{
		"date" : "2015-04-28",
		"nav" : "233.022000"
    
	},
    
	{
		"date" : "2015-05-06",
		"nav" : "229.578000"
    
	},
    
	{
		"date" : "2015-05-13",
		"nav" : "232.569000"
    
	},
    
	{
		"date" : "2015-05-20",
		"nav" : "236.293000"
    
	},
    
	{
		"date" : "2015-05-27",
		"nav" : "234.368000"
    
	},
    
	{
		"date" : "2015-06-03",
		"nav" : "229.140000"
    
	},
    
	{
		"date" : "2015-06-10",
		"nav" : "230.418000"
    
	},
    
	{
		"date" : "2015-06-17",
		"nav" : "230.480000"
    
	},
    
	{
		"date" : "2015-06-24",
		"nav" : "237.108000"
    
	},
    
	{
		"date" : "2015-07-01",
		"nav" : "238.700000"
    
	},
    
	{
		"date" : "2015-07-08",
		"nav" : "235.356000"
    
	},
    
	{
		"date" : "2015-07-15",
		"nav" : "237.231000"
    
	},
    
	{
		"date" : "2015-07-22",
		"nav" : "241.452000"
    
	},
    
	{
		"date" : "2015-07-29",
		"nav" : "237.964000"
    
	},
    
	{
		"date" : "2015-08-05",
		"nav" : "247.477000"
    
	},
    
	{
		"date" : "2015-08-12",
		"nav" : "240.753000"
    
	},
    
	{
		"date" : "2015-08-19",
		"nav" : "245.857000"
    
	},
    
	{
		"date" : "2015-08-26",
		"nav" : "224.185000"
    
	},
    
	{
		"date" : "2015-09-02",
		"nav" : "222.670000"
    
	},
    
	{
		"date" : "2015-09-09",
		"nav" : "223.790000"
    
	},
    
	{
		"date" : "2015-09-16",
		"nav" : "226.081000"
    
	},
    
	{
		"date" : "2015-09-24",
		"nav" : "223.328000"
    
	},
    
	{
		"date" : "2015-10-05",
		"nav" : "230.106000"
    
	},
    
	{
		"date" : "2015-10-12",
		"nav" : "231.550000"
    
	},
    
	{
		"date" : "2015-10-19",
		"nav" : "234.805000"
    
	},
    
	{
		"date" : "2015-10-27",
		"nav" : "234.693000"
    
	},
    
	{
		"date" : "2015-11-03",
		"nav" : "229.397000"
    
	},
    
	{
		"date" : "2015-11-10",
		"nav" : "225.732000"
    
	},
    
	{
		"date" : "2015-11-19",
		"nav" : "228.291000"
    
	},
    
	{
		"date" : "2015-11-27",
		"nav" : "230.641000"
    
	},
    
	{
		"date" : "2015-12-04",
		"nav" : "226.741000"
    
	},
    
	{
		"date" : "2015-12-11",
		"nav" : "222.350000"
    
	},
    
	{
		"date" : "2015-12-18",
		"nav" : "225.885000"
    
	},
    
	{
		"date" : "2015-12-28",
		"nav" : "230.198000"
    
	},
    
	{
		"date" : "2016-01-04",
		"nav" : "226.195000"
    
	},
    
	{
		"date" : "2016-01-11",
		"nav" : "221.636000"
    
	},
    
	{
		"date" : "2016-01-18",
		"nav" : "212.075000"
    
	},
    
	{
		"date" : "2016-01-25",
		"nav" : "214.605000"
    
	},
    
	{
		"date" : "2016-02-02",
		"nav" : "214.689000"
    
	},
    
	{
		"date" : "2016-02-09",
		"nav" : "209.939000"
    
	},
    
	{
		"date" : "2016-02-16",
		"nav" : "202.330000"
    
	},
    
	{
		"date" : "2016-02-23",
		"nav" : "202.978000"
    
	},
    
	{
		"date" : "2016-03-01",
		"nav" : "207.253000"
    
	},
    
	{
		"date" : "2016-03-09",
		"nav" : "216.114000"
    
	},
    
	{
		"date" : "2016-03-16",
		"nav" : "217.924000"
    
	},
    
	{
		"date" : "2016-03-23",
		"nav" : "226.080000"
    
	},
    
	{
		"date" : "2016-04-01",
		"nav" : "226.614000"
    
	},
    
	{
		"date" : "2016-04-08",
		"nav" : "223.069000"
    
	},
    
	{
		"date" : "2016-04-20",
		"nav" : "233.205000"
    
	},
    
	{
		"date" : "2016-04-27",
		"nav" : "236.393000"
    
	},
    
	{
		"date" : "2016-05-04",
		"nav" : "228.940000"
    
	},
    
	{
		"date" : "2016-05-11",
		"nav" : "232.791000"
    
	},
    
	{
		"date" : "2016-05-18",
		"nav" : "233.741000"
    
	},
    
	{
		"date" : "2016-05-25",
		"nav" : "233.674000"
    
	},
    
	{
		"date" : "2016-06-01",
		"nav" : "242.529000"
    
	},
    
	{
		"date" : "2016-06-08",
		"nav" : "245.908000"
    
	},
    
	{
		"date" : "2016-06-15",
		"nav" : "245.207000"
    
	},
    
	{
		"date" : "2016-06-22",
		"nav" : "245.203000"
    
	},
    
	{
		"date" : "2016-06-29",
		"nav" : "244.465000"
    
	},
    
	{
		"date" : "2016-07-07",
		"nav" : "248.371000"
    
	},
    
	{
		"date" : "2016-07-14",
		"nav" : "254.735000"
    
	},
    
	{
		"date" : "2016-07-21",
		"nav" : "253.196000"
    
	},
    
	{
		"date" : "2016-07-28",
		"nav" : "259.377000"
    
	},
    
	{
		"date" : "2016-08-04",
		"nav" : "254.239000"
    
	},
    
	{
		"date" : "2016-08-11",
		"nav" : "257.139000"
    
	},
    
	{
		"date" : "2016-08-19",
		"nav" : "262.897000"
    
	},
    
	{
		"date" : "2016-08-26",
		"nav" : "260.870000"
    
	},
    
	{
		"date" : "2016-09-02",
		"nav" : "267.151000"
    
	},
    
	{
		"date" : "2016-09-12",
		"nav" : "266.194000"
    
	},
    
	{
		"date" : "2016-09-20",
		"nav" : "267.415000"
    
	},
    
	{
		"date" : "2016-09-27",
		"nav" : "266.899000"
    
	},
    
	{
		"date" : "2016-10-04",
		"nav" : "274.550000"
    
	},
    
	{
		"date" : "2016-10-13",
		"nav" : "270.118000"
    
	},
    
	{
		"date" : "2016-10-20",
		"nav" : "275.445000"
    
	},
    
	{
		"date" : "2016-10-27",
		"nav" : "274.448000"
    
	},
    
	{
		"date" : "2016-11-04",
		"nav" : "266.659000"
    
	}
    
]
