[

	{
		"date" : "2009-11-16",
		"nav" : "85.642600"
    
	},
    
	{
		"date" : "2009-11-25",
		"nav" : "86.823800"
    
	},
    
	{
		"date" : "2009-12-04",
		"nav" : "87.778800"
    
	},
    
	{
		"date" : "2009-12-15",
		"nav" : "87.353400"
    
	},
    
	{
		"date" : "2009-12-24",
		"nav" : "90.112800"
    
	},
    
	{
		"date" : "2010-01-07",
		"nav" : "91.918300"
    
	},
    
	{
		"date" : "2010-01-18",
		"nav" : "92.776100"
    
	},
    
	{
		"date" : "2010-01-28",
		"nav" : "88.758900"
    
	},
    
	{
		"date" : "2010-02-08",
		"nav" : "88.235700"
    
	},
    
	{
		"date" : "2010-02-18",
		"nav" : "89.365000"
    
	},
    
	{
		"date" : "2010-03-02",
		"nav" : "90.527500"
    
	},
    
	{
		"date" : "2010-03-11",
		"nav" : "92.508500"
    
	},
    
	{
		"date" : "2010-03-22",
		"nav" : "93.431800"
    
	},
    
	{
		"date" : "2010-04-01",
		"nav" : "94.639200"
    
	},
    
	{
		"date" : "2010-04-13",
		"nav" : "95.734200"
    
	},
    
	{
		"date" : "2010-04-23",
		"nav" : "95.497900"
    
	},
    
	{
		"date" : "2010-05-04",
		"nav" : "94.556600"
    
	},
    
	{
		"date" : "2010-05-13",
		"nav" : "95.315200"
    
	},
    
	{
		"date" : "2010-05-24",
		"nav" : "92.531900"
    
	},
    
	{
		"date" : "2010-06-02",
		"nav" : "94.512500"
    
	},
    
	{
		"date" : "2010-06-11",
		"nav" : "96.185200"
    
	},
    
	{
		"date" : "2010-06-22",
		"nav" : "98.446300"
    
	},
    
	{
		"date" : "2010-07-01",
		"nav" : "97.762500"
    
	},
    
	{
		"date" : "2010-07-12",
		"nav" : "100.076800"
    
	},
    
	{
		"date" : "2010-07-21",
		"nav" : "100.071000"
    
	},
    
	{
		"date" : "2010-07-30",
		"nav" : "100.143400"
    
	},
    
	{
		"date" : "2010-08-10",
		"nav" : "101.391700"
    
	},
    
	{
		"date" : "2010-08-19",
		"nav" : "101.959200"
    
	},
    
	{
		"date" : "2010-08-30",
		"nav" : "100.843100"
    
	},
    
	{
		"date" : "2010-09-08",
		"nav" : "103.748800"
    
	},
    
	{
		"date" : "2010-09-20",
		"nav" : "106.992200"
    
	},
    
	{
		"date" : "2010-09-29",
		"nav" : "107.573500"
    
	},
    
	{
		"date" : "2010-10-08",
		"nav" : "109.584900"
    
	},
    
	{
		"date" : "2010-10-19",
		"nav" : "108.067600"
    
	},
    
	{
		"date" : "2010-10-28",
		"nav" : "108.406900"
    
	},
    
	{
		"date" : "2010-11-09",
		"nav" : "111.552600"
    
	},
    
	{
		"date" : "2010-11-19",
		"nav" : "107.839200"
    
	},
    
	{
		"date" : "2010-11-30",
		"nav" : "107.253700"
    
	},
    
	{
		"date" : "2010-12-09",
		"nav" : "106.254600"
    
	},
    
	{
		"date" : "2010-12-21",
		"nav" : "108.916300"
    
	},
    
	{
		"date" : "2010-12-30",
		"nav" : "109.988700"
    
	},
    
	{
		"date" : "2011-01-10",
		"nav" : "106.491200"
    
	},
    
	{
		"date" : "2011-01-19",
		"nav" : "106.173600"
    
	},
    
	{
		"date" : "2011-01-31",
		"nav" : "103.879600"
    
	},
    
	{
		"date" : "2011-02-09",
		"nav" : "100.389000"
    
	},
    
	{
		"date" : "2011-02-18",
		"nav" : "103.943400"
    
	},
    
	{
		"date" : "2011-03-01",
		"nav" : "103.916700"
    
	},
    
	{
		"date" : "2011-03-11",
		"nav" : "102.729900"
    
	},
    
	{
		"date" : "2011-03-22",
		"nav" : "102.643200"
    
	},
    
	{
		"date" : "2011-03-31",
		"nav" : "108.152600"
    
	},
    
	{
		"date" : "2011-04-11",
		"nav" : "108.292800"
    
	},
    
	{
		"date" : "2011-04-25",
		"nav" : "109.718900"
    
	},
    
	{
		"date" : "2011-05-04",
		"nav" : "106.176700"
    
	},
    
	{
		"date" : "2011-05-13",
		"nav" : "106.580900"
    
	},
    
	{
		"date" : "2011-05-24",
		"nav" : "103.788800"
    
	},
    
	{
		"date" : "2011-06-02",
		"nav" : "106.640900"
    
	},
    
	{
		"date" : "2011-06-13",
		"nav" : "105.690900"
    
	},
    
	{
		"date" : "2011-06-22",
		"nav" : "102.115600"
    
	},
    
	{
		"date" : "2011-07-01",
		"nav" : "106.765700"
    
	},
    
	{
		"date" : "2011-07-12",
		"nav" : "106.281400"
    
	},
    
	{
		"date" : "2011-07-21",
		"nav" : "106.523900"
    
	},
    
	{
		"date" : "2011-08-01",
		"nav" : "105.902200"
    
	},
    
	{
		"date" : "2011-08-10",
		"nav" : "99.852700"
    
	},
    
	{
		"date" : "2011-08-22",
		"nav" : "93.974200"
    
	},
    
	{
		"date" : "2011-09-02",
		"nav" : "96.310300"
    
	},
    
	{
		"date" : "2011-09-13",
		"nav" : "94.639100"
    
	},
    
	{
		"date" : "2011-09-22",
		"nav" : "94.936900"
    
	},
    
	{
		"date" : "2011-10-03",
		"nav" : "92.862700"
    
	},
    
	{
		"date" : "2011-10-13",
		"nav" : "97.029600"
    
	},
    
	{
		"date" : "2011-10-24",
		"nav" : "97.112400"
    
	},
    
	{
		"date" : "2011-11-04",
		"nav" : "100.131800"
    
	},
    
	{
		"date" : "2011-11-17",
		"nav" : "94.320200"
    
	},
    
	{
		"date" : "2011-11-28",
		"nav" : "94.074100"
    
	},
    
	{
		"date" : "2011-12-08",
		"nav" : "94.779300"
    
	},
    
	{
		"date" : "2011-12-19",
		"nav" : "88.604700"
    
	},
    
	{
		"date" : "2011-12-28",
		"nav" : "88.794500"
    
	},
    
	{
		"date" : "2012-01-06",
		"nav" : "91.837100"
    
	},
    
	{
		"date" : "2012-01-17",
		"nav" : "96.158200"
    
	},
    
	{
		"date" : "2012-01-27",
		"nav" : "100.884100"
    
	},
    
	{
		"date" : "2012-02-07",
		"nav" : "103.197900"
    
	},
    
	{
		"date" : "2012-02-16",
		"nav" : "106.430700"
    
	},
    
	{
		"date" : "2012-02-28",
		"nav" : "104.888600"
    
	},
    
	{
		"date" : "2012-03-09",
		"nav" : "104.424900"
    
	},
    
	{
		"date" : "2012-03-20",
		"nav" : "104.264600"
    
	},
    
	{
		"date" : "2012-03-29",
		"nav" : "103.049700"
    
	},
    
	{
		"date" : "2012-04-11",
		"nav" : "103.678400"
    
	},
    
	{
		"date" : "2012-04-20",
		"nav" : "103.943700"
    
	},
    
	{
		"date" : "2012-05-02",
		"nav" : "103.200000"
    
	},
    
	{
		"date" : "2012-05-11",
		"nav" : "99.093600"
    
	},
    
	{
		"date" : "2012-05-22",
		"nav" : "97.807200"
    
	},
    
	{
		"date" : "2012-05-31",
		"nav" : "99.503700"
    
	},
    
	{
		"date" : "2012-06-11",
		"nav" : "100.588700"
    
	},
    
	{
		"date" : "2012-06-20",
		"nav" : "101.461300"
    
	},
    
	{
		"date" : "2012-06-29",
		"nav" : "104.177300"
    
	},
    
	{
		"date" : "2012-07-10",
		"nav" : "105.743000"
    
	},
    
	{
		"date" : "2012-07-19",
		"nav" : "104.837800"
    
	},
    
	{
		"date" : "2012-07-30",
		"nav" : "103.101000"
    
	},
    
	{
		"date" : "2012-08-08",
		"nav" : "103.829100"
    
	},
    
	{
		"date" : "2012-08-21",
		"nav" : "105.328900"
    
	},
    
	{
		"date" : "2012-08-30",
		"nav" : "104.030400"
    
	},
    
	{
		"date" : "2012-09-10",
		"nav" : "106.495400"
    
	},
    
	{
		"date" : "2012-09-20",
		"nav" : "108.875800"
    
	},
    
	{
		"date" : "2012-10-01",
		"nav" : "110.775900"
    
	},
    
	{
		"date" : "2012-10-11",
		"nav" : "110.232200"
    
	},
    
	{
		"date" : "2012-10-22",
		"nav" : "110.012500"
    
	},
    
	{
		"date" : "2012-11-01",
		"nav" : "107.983900"
    
	},
    
	{
		"date" : "2012-11-12",
		"nav" : "107.741600"
    
	},
    
	{
		"date" : "2012-11-23",
		"nav" : "107.509700"
    
	},
    
	{
		"date" : "2012-12-05",
		"nav" : "111.856300"
    
	},
    
	{
		"date" : "2012-12-14",
		"nav" : "111.153800"
    
	},
    
	{
		"date" : "2012-12-26",
		"nav" : "111.596100"
    
	},
    
	{
		"date" : "2013-01-04",
		"nav" : "115.506100"
    
	},
    
	{
		"date" : "2013-01-15",
		"nav" : "117.456600"
    
	},
    
	{
		"date" : "2013-01-24",
		"nav" : "116.053300"
    
	},
    
	{
		"date" : "2013-02-04",
		"nav" : "114.366300"
    
	},
    
	{
		"date" : "2013-02-13",
		"nav" : "112.434000"
    
	},
    
	{
		"date" : "2013-02-22",
		"nav" : "111.607800"
    
	},
    
	{
		"date" : "2013-03-05",
		"nav" : "110.924000"
    
	},
    
	{
		"date" : "2013-03-14",
		"nav" : "112.216400"
    
	},
    
	{
		"date" : "2013-03-25",
		"nav" : "106.723500"
    
	},
    
	{
		"date" : "2013-04-05",
		"nav" : "106.618100"
    
	},
    
	{
		"date" : "2013-04-16",
		"nav" : "106.210800"
    
	},
    
	{
		"date" : "2013-04-29",
		"nav" : "109.525900"
    
	},
    
	{
		"date" : "2013-05-09",
		"nav" : "111.081500"
    
	},
    
	{
		"date" : "2013-05-20",
		"nav" : "111.497200"
    
	},
    
	{
		"date" : "2013-05-29",
		"nav" : "109.999900"
    
	},
    
	{
		"date" : "2013-06-07",
		"nav" : "108.229800"
    
	},
    
	{
		"date" : "2013-06-18",
		"nav" : "107.189400"
    
	},
    
	{
		"date" : "2013-06-27",
		"nav" : "104.109800"
    
	},
    
	{
		"date" : "2013-07-08",
		"nav" : "105.903600"
    
	},
    
	{
		"date" : "2013-07-17",
		"nav" : "107.969500"
    
	},
    
	{
		"date" : "2013-07-26",
		"nav" : "107.781800"
    
	},
    
	{
		"date" : "2013-08-06",
		"nav" : "103.491700"
    
	},
    
	{
		"date" : "2013-08-19",
		"nav" : "105.814400"
    
	},
    
	{
		"date" : "2013-08-28",
		"nav" : "107.183400"
    
	},
    
	{
		"date" : "2013-09-06",
		"nav" : "111.905400"
    
	},
    
	{
		"date" : "2013-09-18",
		"nav" : "114.168200"
    
	},
    
	{
		"date" : "2013-09-27",
		"nav" : "114.967200"
    
	},
    
	{
		"date" : "2013-10-09",
		"nav" : "118.070000"
    
	},
    
	{
		"date" : "2013-10-21",
		"nav" : "121.872400"
    
	},
    
	{
		"date" : "2013-10-30",
		"nav" : "123.407900"
    
	},
    
	{
		"date" : "2013-11-11",
		"nav" : "124.516900"
    
	},
    
	{
		"date" : "2013-11-21",
		"nav" : "123.757600"
    
	},
    
	{
		"date" : "2013-12-02",
		"nav" : "126.426900"
    
	},
    
	{
		"date" : "2013-12-11",
		"nav" : "128.589800"
    
	},
    
	{
		"date" : "2013-12-20",
		"nav" : "129.275700"
    
	},
    
	{
		"date" : "2014-01-01",
		"nav" : "131.265400"
    
	},
    
	{
		"date" : "2014-01-10",
		"nav" : "129.328100"
    
	},
    
	{
		"date" : "2014-01-21",
		"nav" : "130.843200"
    
	},
    
	{
		"date" : "2014-01-30",
		"nav" : "125.847000"
    
	},
    
	{
		"date" : "2014-02-10",
		"nav" : "127.468400"
    
	},
    
	{
		"date" : "2014-02-19",
		"nav" : "128.605000"
    
	},
    
	{
		"date" : "2014-03-03",
		"nav" : "129.120400"
    
	},
    
	{
		"date" : "2014-03-12",
		"nav" : "134.580100"
    
	},
    
	{
		"date" : "2014-03-24",
		"nav" : "136.287800"
    
	},
    
	{
		"date" : "2014-04-02",
		"nav" : "140.389700"
    
	},
    
	{
		"date" : "2014-04-15",
		"nav" : "141.315400"
    
	},
    
	{
		"date" : "2014-04-28",
		"nav" : "142.390800"
    
	},
    
	{
		"date" : "2014-05-08",
		"nav" : "141.588600"
    
	},
    
	{
		"date" : "2014-05-19",
		"nav" : "151.347700"
    
	},
    
	{
		"date" : "2014-05-28",
		"nav" : "154.938400"
    
	},
    
	{
		"date" : "2014-06-06",
		"nav" : "160.819800"
    
	},
    
	{
		"date" : "2014-06-17",
		"nav" : "166.217000"
    
	},
    
	{
		"date" : "2014-06-26",
		"nav" : "164.650600"
    
	},
    
	{
		"date" : "2014-07-07",
		"nav" : "171.466900"
    
	},
    
	{
		"date" : "2014-07-16",
		"nav" : "167.398900"
    
	},
    
	{
		"date" : "2014-07-25",
		"nav" : "168.099000"
    
	},
    
	{
		"date" : "2014-08-06",
		"nav" : "168.061900"
    
	},
    
	{
		"date" : "2014-08-18",
		"nav" : "170.509000"
    
	},
    
	{
		"date" : "2014-08-27",
		"nav" : "171.627300"
    
	},
    
	{
		"date" : "2014-09-08",
		"nav" : "177.586000"
    
	},
    
	{
		"date" : "2014-09-17",
		"nav" : "176.798300"
    
	},
    
	{
		"date" : "2014-09-26",
		"nav" : "174.705200"
    
	},
    
	{
		"date" : "2014-10-10",
		"nav" : "174.048200"
    
	},
    
	{
		"date" : "2014-10-22",
		"nav" : "177.245600"
    
	},
    
	{
		"date" : "2014-11-05",
		"nav" : "182.282600"
    
	},
    
	{
		"date" : "2014-11-17",
		"nav" : "183.931300"
    
	},
    
	{
		"date" : "2014-11-26",
		"nav" : "184.669500"
    
	},
    
	{
		"date" : "2014-12-05",
		"nav" : "186.335000"
    
	},
    
	{
		"date" : "2014-12-16",
		"nav" : "177.325800"
    
	},
    
	{
		"date" : "2014-12-26",
		"nav" : "181.081500"
    
	},
    
	{
		"date" : "2015-01-06",
		"nav" : "180.649800"
    
	},
    
	{
		"date" : "2015-01-15",
		"nav" : "186.123500"
    
	},
    
	{
		"date" : "2015-01-27",
		"nav" : "192.458700"
    
	},
    
	{
		"date" : "2015-02-05",
		"nav" : "189.990400"
    
	},
    
	{
		"date" : "2015-02-16",
		"nav" : "192.615800"
    
	},
    
	{
		"date" : "2015-02-26",
		"nav" : "190.529000"
    
	},
    
	{
		"date" : "2015-03-10",
		"nav" : "190.695400"
    
	},
    
	{
		"date" : "2015-03-19",
		"nav" : "189.654600"
    
	},
    
	{
		"date" : "2015-03-30",
		"nav" : "186.951000"
    
	},
    
	{
		"date" : "2015-04-10",
		"nav" : "193.169100"
    
	},
    
	{
		"date" : "2015-04-22",
		"nav" : "187.222700"
    
	},
    
	{
		"date" : "2015-05-04",
		"nav" : "186.290000"
    
	},
    
	{
		"date" : "2015-05-13",
		"nav" : "184.718200"
    
	},
    
	{
		"date" : "2015-05-22",
		"nav" : "188.372400"
    
	},
    
	{
		"date" : "2015-06-02",
		"nav" : "183.722600"
    
	},
    
	{
		"date" : "2015-06-11",
		"nav" : "179.980300"
    
	},
    
	{
		"date" : "2015-06-22",
		"nav" : "183.878200"
    
	},
    
	{
		"date" : "2015-07-01",
		"nav" : "183.222000"
    
	},
    
	{
		"date" : "2015-07-10",
		"nav" : "180.500900"
    
	},
    
	{
		"date" : "2015-07-21",
		"nav" : "183.458000"
    
	},
    
	{
		"date" : "2015-07-30",
		"nav" : "183.280500"
    
	},
    
	{
		"date" : "2015-08-10",
		"nav" : "185.317900"
    
	},
    
	{
		"date" : "2015-08-19",
		"nav" : "183.442300"
    
	},
    
	{
		"date" : "2015-08-28",
		"nav" : "174.954000"
    
	},
    
	{
		"date" : "2015-09-08",
		"nav" : "168.659600"
    
	},
    
	{
		"date" : "2015-09-18",
		"nav" : "176.058600"
    
	},
    
	{
		"date" : "2015-09-30",
		"nav" : "173.810400"
    
	},
    
	{
		"date" : "2015-10-12",
		"nav" : "180.761100"
    
	},
    
	{
		"date" : "2015-10-21",
		"nav" : "183.040200"
    
	},
    
	{
		"date" : "2015-11-02",
		"nav" : "180.536500"
    
	},
    
	{
		"date" : "2015-11-13",
		"nav" : "177.247700"
    
	},
    
	{
		"date" : "2015-11-24",
		"nav" : "178.459700"
    
	},
    
	{
		"date" : "2015-12-04",
		"nav" : "178.311900"
    
	},
    
	{
		"date" : "2015-12-15",
		"nav" : "174.155500"
    
	},
    
	{
		"date" : "2015-12-24",
		"nav" : "179.323700"
    
	},
    
	{
		"date" : "2016-01-05",
		"nav" : "178.926300"
    
	},
    
	{
		"date" : "2016-01-14",
		"nav" : "172.637500"
    
	},
    
	{
		"date" : "2016-01-25",
		"nav" : "168.716700"
    
	},
    
	{
		"date" : "2016-02-04",
		"nav" : "168.427000"
    
	},
    
	{
		"date" : "2016-02-15",
		"nav" : "162.614200"
    
	},
    
	{
		"date" : "2016-02-24",
		"nav" : "159.059200"
    
	},
    
	{
		"date" : "2016-03-04",
		"nav" : "167.737200"
    
	},
    
	{
		"date" : "2016-03-16",
		"nav" : "168.817300"
    
	},
    
	{
		"date" : "2016-03-29",
		"nav" : "170.206000"
    
	},
    
	{
		"date" : "2016-04-07",
		"nav" : "172.593000"
    
	},
    
	{
		"date" : "2016-04-21",
		"nav" : "180.443600"
    
	},
    
	{
		"date" : "2016-05-02",
		"nav" : "179.982500"
    
	},
    
	{
		"date" : "2016-05-11",
		"nav" : "178.709000"
    
	},
    
	{
		"date" : "2016-05-20",
		"nav" : "178.259000"
    
	},
    
	{
		"date" : "2016-05-31",
		"nav" : "181.863900"
    
	},
    
	{
		"date" : "2016-06-09",
		"nav" : "184.024500"
    
	},
    
	{
		"date" : "2016-06-20",
		"nav" : "185.522500"
    
	},
    
	{
		"date" : "2016-06-29",
		"nav" : "187.307600"
    
	},
    
	{
		"date" : "2016-07-11",
		"nav" : "192.390900"
    
	},
    
	{
		"date" : "2016-07-20",
		"nav" : "196.217000"
    
	},
    
	{
		"date" : "2016-07-29",
		"nav" : "197.568400"
    
	},
    
	{
		"date" : "2016-08-09",
		"nav" : "199.659200"
    
	},
    
	{
		"date" : "2016-08-19",
		"nav" : "203.217600"
    
	},
    
	{
		"date" : "2016-08-30",
		"nav" : "206.349800"
    
	},
    
	{
		"date" : "2016-09-09",
		"nav" : "207.199800"
    
	},
    
	{
		"date" : "2016-09-21",
		"nav" : "206.385000"
    
	},
    
	{
		"date" : "2016-09-30",
		"nav" : "203.070300"
    
	},
    
	{
		"date" : "2016-10-13",
		"nav" : "204.341400"
    
	},
    
	{
		"date" : "2016-10-24",
		"nav" : "206.659400"
    
	},
    
	{
		"date" : "2016-11-03",
		"nav" : "202.812600"
    
	}
    
]
