[

	{
		"date" : "2009-09-22",
		"nav" : "12.734500"
    
	},
    
	{
		"date" : "2009-10-05",
		"nav" : "12.817800"
    
	},
    
	{
		"date" : "2009-10-15",
		"nav" : "13.326400"
    
	},
    
	{
		"date" : "2009-10-27",
		"nav" : "12.896200"
    
	},
    
	{
		"date" : "2009-11-06",
		"nav" : "13.066300"
    
	},
    
	{
		"date" : "2009-11-17",
		"nav" : "13.589200"
    
	},
    
	{
		"date" : "2009-11-26",
		"nav" : "13.474500"
    
	},
    
	{
		"date" : "2009-12-07",
		"nav" : "13.632500"
    
	},
    
	{
		"date" : "2009-12-16",
		"nav" : "13.517800"
    
	},
    
	{
		"date" : "2009-12-29",
		"nav" : "13.850300"
    
	},
    
	{
		"date" : "2010-01-08",
		"nav" : "14.102000"
    
	},
    
	{
		"date" : "2010-01-19",
		"nav" : "14.156600"
    
	},
    
	{
		"date" : "2010-01-29",
		"nav" : "13.271900"
    
	},
    
	{
		"date" : "2010-02-09",
		"nav" : "13.285500"
    
	},
    
	{
		"date" : "2010-02-19",
		"nav" : "13.451000"
    
	},
    
	{
		"date" : "2010-03-03",
		"nav" : "13.869000"
    
	},
    
	{
		"date" : "2010-03-12",
		"nav" : "14.030600"
    
	},
    
	{
		"date" : "2010-03-23",
		"nav" : "14.200100"
    
	},
    
	{
		"date" : "2010-04-05",
		"nav" : "14.595600"
    
	},
    
	{
		"date" : "2010-04-15",
		"nav" : "14.623900"
    
	},
    
	{
		"date" : "2010-04-26",
		"nav" : "14.820400"
    
	},
    
	{
		"date" : "2010-05-05",
		"nav" : "14.433100"
    
	},
    
	{
		"date" : "2010-05-14",
		"nav" : "14.344000"
    
	},
    
	{
		"date" : "2010-05-25",
		"nav" : "13.507600"
    
	},
    
	{
		"date" : "2010-06-03",
		"nav" : "14.300800"
    
	},
    
	{
		"date" : "2010-06-14",
		"nav" : "14.517000"
    
	},
    
	{
		"date" : "2010-06-23",
		"nav" : "14.768400"
    
	},
    
	{
		"date" : "2010-07-02",
		"nav" : "14.640700"
    
	},
    
	{
		"date" : "2010-07-13",
		"nav" : "15.132500"
    
	},
    
	{
		"date" : "2010-07-22",
		"nav" : "15.380100"
    
	},
    
	{
		"date" : "2010-08-02",
		"nav" : "15.308800"
    
	},
    
	{
		"date" : "2010-08-11",
		"nav" : "15.258300"
    
	},
    
	{
		"date" : "2010-08-20",
		"nav" : "15.399400"
    
	},
    
	{
		"date" : "2010-08-31",
		"nav" : "15.140600"
    
	},
    
	{
		"date" : "2010-09-09",
		"nav" : "16.031600"
    
	},
    
	{
		"date" : "2010-09-21",
		"nav" : "16.253300"
    
	},
    
	{
		"date" : "2010-09-30",
		"nav" : "16.168300"
    
	},
    
	{
		"date" : "2010-10-11",
		"nav" : "16.567000"
    
	},
    
	{
		"date" : "2010-10-20",
		"nav" : "16.147100"
    
	},
    
	{
		"date" : "2010-10-29",
		"nav" : "16.209300"
    
	},
    
	{
		"date" : "2010-11-10",
		"nav" : "16.764800"
    
	},
    
	{
		"date" : "2010-11-22",
		"nav" : "16.084000"
    
	},
    
	{
		"date" : "2010-12-01",
		"nav" : "15.955700"
    
	},
    
	{
		"date" : "2010-12-10",
		"nav" : "15.224700"
    
	},
    
	{
		"date" : "2010-12-22",
		"nav" : "15.444800"
    
	},
    
	{
		"date" : "2010-12-31",
		"nav" : "15.762900"
    
	},
    
	{
		"date" : "2011-01-11",
		"nav" : "15.043800"
    
	},
    
	{
		"date" : "2011-01-20",
		"nav" : "14.926900"
    
	},
    
	{
		"date" : "2011-02-01",
		"nav" : "14.177300"
    
	},
    
	{
		"date" : "2011-02-10",
		"nav" : "13.599200"
    
	},
    
	{
		"date" : "2011-02-21",
		"nav" : "14.326200"
    
	},
    
	{
		"date" : "2011-03-03",
		"nav" : "14.044400"
    
	},
    
	{
		"date" : "2011-03-14",
		"nav" : "14.043900"
    
	},
    
	{
		"date" : "2011-03-23",
		"nav" : "14.018300"
    
	},
    
	{
		"date" : "2011-04-01",
		"nav" : "14.775800"
    
	},
    
	{
		"date" : "2011-04-13",
		"nav" : "15.173600"
    
	},
    
	{
		"date" : "2011-04-26",
		"nav" : "15.205900"
    
	},
    
	{
		"date" : "2011-05-05",
		"nav" : "14.330400"
    
	},
    
	{
		"date" : "2011-05-16",
		"nav" : "14.426000"
    
	},
    
	{
		"date" : "2011-05-25",
		"nav" : "14.104600"
    
	},
    
	{
		"date" : "2011-06-03",
		"nav" : "14.488300"
    
	},
    
	{
		"date" : "2011-06-14",
		"nav" : "14.635000"
    
	},
    
	{
		"date" : "2011-06-23",
		"nav" : "13.987000"
    
	},
    
	{
		"date" : "2011-07-04",
		"nav" : "14.707500"
    
	},
    
	{
		"date" : "2011-07-13",
		"nav" : "14.632400"
    
	},
    
	{
		"date" : "2011-07-22",
		"nav" : "14.693600"
    
	},
    
	{
		"date" : "2011-08-02",
		"nav" : "14.200000"
    
	},
    
	{
		"date" : "2011-08-11",
		"nav" : "13.710600"
    
	},
    
	{
		"date" : "2011-08-23",
		"nav" : "13.315900"
    
	},
    
	{
		"date" : "2011-09-05",
		"nav" : "13.304400"
    
	},
    
	{
		"date" : "2011-09-14",
		"nav" : "13.348800"
    
	},
    
	{
		"date" : "2011-09-23",
		"nav" : "13.205500"
    
	},
    
	{
		"date" : "2011-10-04",
		"nav" : "12.937300"
    
	},
    
	{
		"date" : "2011-10-14",
		"nav" : "13.417700"
    
	},
    
	{
		"date" : "2011-10-25",
		"nav" : "13.313400"
    
	},
    
	{
		"date" : "2011-11-08",
		"nav" : "13.628700"
    
	},
    
	{
		"date" : "2011-11-18",
		"nav" : "12.694400"
    
	},
    
	{
		"date" : "2011-11-29",
		"nav" : "12.570000"
    
	},
    
	{
		"date" : "2011-12-09",
		"nav" : "12.454000"
    
	},
    
	{
		"date" : "2011-12-20",
		"nav" : "11.608000"
    
	},
    
	{
		"date" : "2011-12-29",
		"nav" : "11.863200"
    
	},
    
	{
		"date" : "2012-01-09",
		"nav" : "12.209900"
    
	},
    
	{
		"date" : "2012-01-18",
		"nav" : "12.440200"
    
	},
    
	{
		"date" : "2012-01-30",
		"nav" : "12.870600"
    
	},
    
	{
		"date" : "2012-02-08",
		"nav" : "13.570100"
    
	},
    
	{
		"date" : "2012-02-17",
		"nav" : "14.032800"
    
	}
    
]
